calciumflexanalysis/__init__.py
calciumflexanalysis/calcium_flex.py
calciumflexanalysis/multiplate.py
calciumflexanalysis-1.2.0.dist-info/LICENSE
calciumflexanalysis-1.2.0.dist-info/METADATA
calciumflexanalysis-1.2.0.dist-info/WHEEL
calciumflexanalysis-1.2.0.dist-info/top_level.txt
calciumflexanalysis-1.2.0.dist-info/RECORD
